fit/__init__.py
fit/exceptions.py
fit/models.py
fit/scripts/__init__.py
fit/scripts/fit.py
fit_cli-0.1.0.dist-info/LICENSE
fit_cli-0.1.0.dist-info/METADATA
fit_cli-0.1.0.dist-info/WHEEL
fit_cli-0.1.0.dist-info/entry_points.txt
fit_cli-0.1.0.dist-info/top_level.txt
fit_cli-0.1.0.dist-info/RECORD
