Metadata-Version: 2.1
Name: fit-cli
Version: 0.1.0
Summary: A command line utility for organizing directories of binary content.
Home-page: https://github.com/jakeledoux/fit-cli
Author: Jake Ledoux
Author-email: contactjakeledoux@gmail.com
License: GNU General Public License v2.0
Platform: UNKNOWN
Requires-Dist: click (>=7.1.2)
Requires-Dist: imageio (>=2.9.0)
Requires-Dist: numpy (>=1.20.1)
Requires-Dist: Pillow (>=8.1.0)
Requires-Dist: SQLAlchemy (>=1.3.23)
